tiny_graph/__init__.py
tiny_graph/edge.py
tiny_graph/helper.py
tiny_graph/node.py
tiny_graph/driver/__init__.py
tiny_graph/driver/base.py
tiny_graph/driver/neo4j.py
tiny_graph/graph/__init__.py
tiny_graph/graph/base.py
tiny_graph/graph/multi_layer_graph/__init__.py
tiny_graph/graph/multi_layer_graph/edges.py
tiny_graph/graph/multi_layer_graph/multi_layer_graph.py
tiny_graph/graph/multi_layer_graph/nodes.py
tiny_graph/graph/multi_layer_graph/types.py
tiny_graph/graph/multi_layer_graph/core/edge.py
tiny_graph/graph/multi_layer_graph/core/node.py
tiny_graph/graph/multi_layer_graph/datamodels/clients.py
tiny_graph/graph/multi_layer_graph/datamodels/extract_nodes.py
tiny_graph/graph/multi_layer_graph/ops/cluster_operations.py
tiny_graph/graph/multi_layer_graph/ops/edge_operations.py
tiny_graph/graph/multi_layer_graph/ops/graph_operations.py
tiny_graph/graph/multi_layer_graph/ops/node_operations.py
tiny_graph/graph/multi_layer_graph/prompts/clusters.py
tiny_graph/graph/multi_layer_graph/prompts/default_prompts.py
tiny_graph/graph/multi_layer_graph/prompts/edges.py
tiny_graph/graph/multi_layer_graph/prompts/nodes.py
tiny_graph/graph/multi_layer_graph/queries/cluster_queries.py
tiny_graph/graph/multi_layer_graph/queries/edge_queries.py
tiny_graph/graph/multi_layer_graph/queries/graph_queries.py
tiny_graph/graph/multi_layer_graph/queries/node_queries.py
tiny_graph/graph/multi_layer_graph/search/__init__.py
tiny_graph/graph/multi_layer_graph/search/search.py
tiny_graph/graph/multi_layer_graph/search/search_cfg.py
tiny_graph/graph/multi_layer_graph/search/search_presets.py
tiny_graph/graph/multi_layer_graph/search/search_ranker.py
tiny_graph/graph/multi_layer_graph/search/search_utils.py
tiny_graph/graph/multi_layer_graph/utils/custom_types.py
tiny_graph/graph/multi_layer_graph/utils/model_repr.py
tiny_graph/graph/multi_layer_graph/utils/node_formatter.py
tiny_graph/graph/multi_layer_graph/utils/text_similarity.py
tiny_graph/types/provider.py
tinygent_graph-0.1.1007.dist-info/METADATA
tinygent_graph-0.1.1007.dist-info/WHEEL
tinygent_graph-0.1.1007.dist-info/RECORD
