Metadata-Version: 2.4
Name: tinygent-graph
Version: 0.1.1007
Requires-Dist: neo4j>=6.0.3
Requires-Dist: tinygent
